MANIFEST.in
README.txt
setup.py
camcrypt/__init__.py
camcrypt.egg-info/PKG-INFO
camcrypt.egg-info/SOURCES.txt
camcrypt.egg-info/dependency_links.txt
camcrypt.egg-info/top_level.txt
camellia-GPL-1.2.0/COPYING
camellia-GPL-1.2.0/README
camellia-GPL-1.2.0/camellia.c
camellia-GPL-1.2.0/camellia.h