Metadata-Version: 1.1
Name: camcrypt
Version: 1.2.0
Summary: Python wrapper around the Camellia encryption library
Home-page: http://github.com/knowmalware/camcrypt
Author: Frank Poz
Author-email: knowmalware@gmail.com
License: UNKNOWN
Platform: UNKNOWN
Classifier: Programming Language :: Python
Classifier: Development Status :: 4 - Beta
Classifier: Intended Audience :: Developers
Classifier: Operating System :: OS Independent
